.env.sample
MANIFEST.in
README.md
requirements.txt
setup.py
byb/__init__.py
byb/cli.py
byb/core.py
byb/settings.py
byb.egg-info/PKG-INFO
byb.egg-info/SOURCES.txt
byb.egg-info/dependency_links.txt
byb.egg-info/entry_points.txt
byb.egg-info/requires.txt
byb.egg-info/top_level.txt
byb/bots/__init__.py
byb/bots/core.py
byb/bots/geocities_archive_crawler.py
byb/bots/rss_feed.py
byb/bots/synth_oclock.py
byb/bots/assets/synths.csv
byb/platforms/__init__.py
byb/platforms/gitlab.py
byb/platforms/instagram.py
byb/utils/__init__.py
byb/utils/browser.py
byb/utils/image.py
byb/utils/path.py
tests/__init__.py
tests/test_core.py
tests/test_platforms.py