Metadata-Version: 2.1
Name: byb
Version: 0.0.1
Summary: byb
Home-page: https://byb.globally.ltd
Author: Globally Limited
Author-email: dev@globally.ltd
